gaussf_pipeline/__init__.py
gaussf_pipeline/gaussf_tpm.py
gaussf_pipeline/kmer_counter.py
gaussf_pipeline/kmer_freq_dist.py
gaussf_pipeline/merge_normalize.py
gaussf_pipeline-0.1.0.dist-info/METADATA
gaussf_pipeline-0.1.0.dist-info/WHEEL
gaussf_pipeline-0.1.0.dist-info/entry_points.txt
gaussf_pipeline-0.1.0.dist-info/top_level.txt
gaussf_pipeline-0.1.0.dist-info/RECORD
