Metadata-Version: 2.1
Name: gaussf-pipeline
Version: 0.1.0
Summary: Pipeline for transcript abundance estimation using Gaussian smoothing of k-mer frequencies.
Author-email: Qiang Su <qiang_su@hotmail.com>
License: MIT License
Project-URL: Homepage, https://github.com/QiangSu/gaussf_pipeline
Project-URL: Repository, https://github.com/QiangSu/gaussf_pipeline
Project-URL: Bug Tracker, https://github.com/QiangSu/gaussf_pipeline/issues
Classifier: Development Status :: 3 - Alpha
Classifier: Programming Language :: Python :: 3
Classifier: Programming Language :: Python :: 3.8
Classifier: Programming Language :: Python :: 3.9
Classifier: Programming Language :: Python :: 3.10
Classifier: Programming Language :: Python :: 3.11
Classifier: Programming Language :: Python :: 3.12
Classifier: Operating System :: POSIX :: Linux
Classifier: Intended Audience :: Science/Research
Classifier: Topic :: Scientific/Engineering :: Bio-Informatics
Classifier: Natural Language :: English
Requires-Python: >=3.8
Requires-Dist: pandas>=1.0
Requires-Dist: scipy>=1.0
Requires-Dist: tqdm>=4.0
Requires-Dist: numpy>=1.18
